Metadata-Version: 2.1
Name: Brightify
Version: 0.1.13
Summary: Brightify is an OS-independent application that adjusts monitor brightness using the DDC/CI protocol and custom protocols for USB monitors, featuring a brightness sensor for automatic adjustments based on ambient light, and can be controlled via a taskbar icon.
Author-email: "Robin S." <brightify@rs-web.net>
Keywords: brightness,monitor,screen,control,tool
Requires-Python: >=3.11
Requires-Dist: platformio
Requires-Dist: pyserial
Requires-Dist: libusb1
Requires-Dist: PyQt6
Requires-Dist: pyudev ; platform_system == "Linux"
Requires-Dist: pywin32 ; platform_system == "Windows"
Requires-Dist: winshell ; platform_system == "Windows"
Requires-Dist: wmi ; platform_system == "Windows"
